{"nodes": [{"id": "d_github_realmcrafterorigins_skeletalanimation_master_lib_assimp_contrib_utf8cpp_source_utf8_core_h", "label": "core.h", "file_type": "code", "source_file": "D:\\Github\\RealmCrafterOrigins\\SkeletalAnimation-master\\lib\\assimp\\contrib\\utf8cpp\\source\\utf8\\core.h", "source_location": "L1"}, {"id": "utf8_core_utf8", "label": "utf8()", "file_type": "code", "source_file": "D:\\Github\\RealmCrafterOrigins\\SkeletalAnimation-master\\lib\\assimp\\contrib\\utf8cpp\\source\\utf8\\core.h", "source_location": "L33"}], "edges": [{"source": "d_github_realmcrafterorigins_skeletalanimation_master_lib_assimp_contrib_utf8cpp_source_utf8_core_h", "target": "iterator", "relation": "imports", "context": "import", "confidence": "EXTRACTED", "source_file": "D:\\Github\\RealmCrafterOrigins\\SkeletalAnimation-master\\lib\\assimp\\contrib\\utf8cpp\\source\\utf8\\core.h", "source_location": "L31", "weight": 1.0}, {"source": "d_github_realmcrafterorigins_skeletalanimation_master_lib_assimp_contrib_utf8cpp_source_utf8_core_h", "target": "utf8_core_utf8", "relation": "contains", "confidence": "EXTRACTED", "source_file": "D:\\Github\\RealmCrafterOrigins\\SkeletalAnimation-master\\lib\\assimp\\contrib\\utf8cpp\\source\\utf8\\core.h", "source_location": "L33", "weight": 1.0}], "raw_calls": [{"caller_nid": "utf8_core_utf8", "callee": "validate_next", "is_member_call": false, "source_file": "D:\\Github\\RealmCrafterOrigins\\SkeletalAnimation-master\\lib\\assimp\\contrib\\utf8cpp\\source\\utf8\\core.h", "source_location": "L292"}]}