{"nodes": [{"id": "d_github_realmcrafterorigins_skeletalanimation_master_lib_assimp_code_ms3d_ms3dloader_cpp", "label": "MS3DLoader.cpp", "file_type": "code", "source_file": "D:\\Github\\RealmCrafterOrigins\\SkeletalAnimation-master\\lib\\assimp\\code\\MS3D\\MS3DLoader.cpp", "source_location": "L1"}, {"id": "ms3d_ms3dloader_ms3dimporter", "label": "MS3DImporter()", "file_type": "code", "source_file": "D:\\Github\\RealmCrafterOrigins\\SkeletalAnimation-master\\lib\\assimp\\code\\MS3D\\MS3DLoader.cpp", "source_location": "L83"}, {"id": "ms3d_ms3dloader_canread", "label": "CanRead()", "file_type": "code", "source_file": "D:\\Github\\RealmCrafterOrigins\\SkeletalAnimation-master\\lib\\assimp\\code\\MS3D\\MS3DLoader.cpp", "source_location": "L94"}, {"id": "ms3d_ms3dloader_getinfo", "label": "GetInfo()", "file_type": "code", "source_file": "D:\\Github\\RealmCrafterOrigins\\SkeletalAnimation-master\\lib\\assimp\\code\\MS3D\\MS3DLoader.cpp", "source_location": "L114"}, {"id": "ms3d_ms3dloader_readcolor", "label": "ReadColor()", "file_type": "code", "source_file": "D:\\Github\\RealmCrafterOrigins\\SkeletalAnimation-master\\lib\\assimp\\code\\MS3D\\MS3DLoader.cpp", "source_location": "L120"}, {"id": "ms3d_ms3dloader_readvector", "label": "ReadVector()", "file_type": "code", "source_file": "D:\\Github\\RealmCrafterOrigins\\SkeletalAnimation-master\\lib\\assimp\\code\\MS3D\\MS3DLoader.cpp", "source_location": "L127"}, {"id": "ms3d_ms3dloader_readcomments", "label": "ReadComments()", "file_type": "code", "source_file": "D:\\Github\\RealmCrafterOrigins\\SkeletalAnimation-master\\lib\\assimp\\code\\MS3D\\MS3DLoader.cpp", "source_location": "L135"}, {"id": "ms3d_ms3dloader_inrange", "label": "inrange()", "file_type": "code", "source_file": "D:\\Github\\RealmCrafterOrigins\\SkeletalAnimation-master\\lib\\assimp\\code\\MS3D\\MS3DLoader.cpp", "source_location": "L158"}, {"id": "ms3d_ms3dloader_collectchildjoints", "label": "CollectChildJoints()", "file_type": "code", "source_file": "D:\\Github\\RealmCrafterOrigins\\SkeletalAnimation-master\\lib\\assimp\\code\\MS3D\\MS3DLoader.cpp", "source_location": "L164"}, {"id": "ms3d_ms3dloader_internreadfile", "label": "InternReadFile()", "file_type": "code", "source_file": "D:\\Github\\RealmCrafterOrigins\\SkeletalAnimation-master\\lib\\assimp\\code\\MS3D\\MS3DLoader.cpp", "source_location": "L215"}], "edges": [{"source": "d_github_realmcrafterorigins_skeletalanimation_master_lib_assimp_code_ms3d_ms3dloader_cpp", "target": "ms3dloader", "relation": "imports", "context": "import", "confidence": "EXTRACTED", "source_file": "D:\\Github\\RealmCrafterOrigins\\SkeletalAnimation-master\\lib\\assimp\\code\\MS3D\\MS3DLoader.cpp", "source_location": "L53", "weight": 1.0}, {"source": "d_github_realmcrafterorigins_skeletalanimation_master_lib_assimp_code_ms3d_ms3dloader_cpp", "target": "streamreader", "relation": "imports", "context": "import", "confidence": "EXTRACTED", "source_file": "D:\\Github\\RealmCrafterOrigins\\SkeletalAnimation-master\\lib\\assimp\\code\\MS3D\\MS3DLoader.cpp", "source_location": "L54", "weight": 1.0}, {"source": "d_github_realmcrafterorigins_skeletalanimation_master_lib_assimp_code_ms3d_ms3dloader_cpp", "target": "defaultlogger", "relation": "imports", "context": "import", "confidence": "EXTRACTED", "source_file": "D:\\Github\\RealmCrafterOrigins\\SkeletalAnimation-master\\lib\\assimp\\code\\MS3D\\MS3DLoader.cpp", "source_location": "L55", "weight": 1.0}, {"source": "d_github_realmcrafterorigins_skeletalanimation_master_lib_assimp_code_ms3d_ms3dloader_cpp", "target": "scene", "relation": "imports", "context": "import", "confidence": "EXTRACTED", "source_file": "D:\\Github\\RealmCrafterOrigins\\SkeletalAnimation-master\\lib\\assimp\\code\\MS3D\\MS3DLoader.cpp", "source_location": "L56", "weight": 1.0}, {"source": "d_github_realmcrafterorigins_skeletalanimation_master_lib_assimp_code_ms3d_ms3dloader_cpp", "target": "iosystem", "relation": "imports", "context": "import", "confidence": "EXTRACTED", "source_file": "D:\\Github\\RealmCrafterOrigins\\SkeletalAnimation-master\\lib\\assimp\\code\\MS3D\\MS3DLoader.cpp", "source_location": "L57", "weight": 1.0}, {"source": "d_github_realmcrafterorigins_skeletalanimation_master_lib_assimp_code_ms3d_ms3dloader_cpp", "target": "importerdesc", "relation": "imports", "context": "import", "confidence": "EXTRACTED", "source_file": "D:\\Github\\RealmCrafterOrigins\\SkeletalAnimation-master\\lib\\assimp\\code\\MS3D\\MS3DLoader.cpp", "source_location": "L58", "weight": 1.0}, {"source": "d_github_realmcrafterorigins_skeletalanimation_master_lib_assimp_code_ms3d_ms3dloader_cpp", "target": "map", "relation": "imports", "context": "import", "confidence": "EXTRACTED", "source_file": "D:\\Github\\RealmCrafterOrigins\\SkeletalAnimation-master\\lib\\assimp\\code\\MS3D\\MS3DLoader.cpp", "source_location": "L59", "weight": 1.0}, {"source": "d_github_realmcrafterorigins_skeletalanimation_master_lib_assimp_code_ms3d_ms3dloader_cpp", "target": "ms3d_ms3dloader_ms3dimporter", "relation": "contains", "confidence": "EXTRACTED", "source_file": "D:\\Github\\RealmCrafterOrigins\\SkeletalAnimation-master\\lib\\assimp\\code\\MS3D\\MS3DLoader.cpp", "source_location": "L83", "weight": 1.0}, {"source": "d_github_realmcrafterorigins_skeletalanimation_master_lib_assimp_code_ms3d_ms3dloader_cpp", "target": "ms3d_ms3dloader_ms3dimporter", "relation": "contains", "confidence": "EXTRACTED", "source_file": "D:\\Github\\RealmCrafterOrigins\\SkeletalAnimation-master\\lib\\assimp\\code\\MS3D\\MS3DLoader.cpp", "source_location": "L89", "weight": 1.0}, {"source": "d_github_realmcrafterorigins_skeletalanimation_master_lib_assimp_code_ms3d_ms3dloader_cpp", "target": "ms3d_ms3dloader_canread", "relation": "contains", "confidence": "EXTRACTED", "source_file": "D:\\Github\\RealmCrafterOrigins\\SkeletalAnimation-master\\lib\\assimp\\code\\MS3D\\MS3DLoader.cpp", "source_location": "L94", "weight": 1.0}, {"source": "d_github_realmcrafterorigins_skeletalanimation_master_lib_assimp_code_ms3d_ms3dloader_cpp", "target": "ms3d_ms3dloader_getinfo", "relation": "contains", "confidence": "EXTRACTED", "source_file": "D:\\Github\\RealmCrafterOrigins\\SkeletalAnimation-master\\lib\\assimp\\code\\MS3D\\MS3DLoader.cpp", "source_location": "L114", "weight": 1.0}, {"source": "d_github_realmcrafterorigins_skeletalanimation_master_lib_assimp_code_ms3d_ms3dloader_cpp", "target": "ms3d_ms3dloader_readcolor", "relation": "contains", "confidence": "EXTRACTED", "source_file": "D:\\Github\\RealmCrafterOrigins\\SkeletalAnimation-master\\lib\\assimp\\code\\MS3D\\MS3DLoader.cpp", "source_location": "L120", "weight": 1.0}, {"source": "d_github_realmcrafterorigins_skeletalanimation_master_lib_assimp_code_ms3d_ms3dloader_cpp", "target": "ms3d_ms3dloader_readvector", "relation": "contains", "confidence": "EXTRACTED", "source_file": "D:\\Github\\RealmCrafterOrigins\\SkeletalAnimation-master\\lib\\assimp\\code\\MS3D\\MS3DLoader.cpp", "source_location": "L127", "weight": 1.0}, {"source": "d_github_realmcrafterorigins_skeletalanimation_master_lib_assimp_code_ms3d_ms3dloader_cpp", "target": "ms3d_ms3dloader_readcomments", "relation": "contains", "confidence": "EXTRACTED", "source_file": "D:\\Github\\RealmCrafterOrigins\\SkeletalAnimation-master\\lib\\assimp\\code\\MS3D\\MS3DLoader.cpp", "source_location": "L135", "weight": 1.0}, {"source": "d_github_realmcrafterorigins_skeletalanimation_master_lib_assimp_code_ms3d_ms3dloader_cpp", "target": "ms3d_ms3dloader_inrange", "relation": "contains", "confidence": "EXTRACTED", "source_file": "D:\\Github\\RealmCrafterOrigins\\SkeletalAnimation-master\\lib\\assimp\\code\\MS3D\\MS3DLoader.cpp", "source_location": "L158", "weight": 1.0}, {"source": "d_github_realmcrafterorigins_skeletalanimation_master_lib_assimp_code_ms3d_ms3dloader_cpp", "target": "ms3d_ms3dloader_collectchildjoints", "relation": "contains", "confidence": "EXTRACTED", "source_file": "D:\\Github\\RealmCrafterOrigins\\SkeletalAnimation-master\\lib\\assimp\\code\\MS3D\\MS3DLoader.cpp", "source_location": "L164", "weight": 1.0}, {"source": "d_github_realmcrafterorigins_skeletalanimation_master_lib_assimp_code_ms3d_ms3dloader_cpp", "target": "ms3d_ms3dloader_collectchildjoints", "relation": "contains", "confidence": "EXTRACTED", "source_file": "D:\\Github\\RealmCrafterOrigins\\SkeletalAnimation-master\\lib\\assimp\\code\\MS3D\\MS3DLoader.cpp", "source_location": "L205", "weight": 1.0}, {"source": "d_github_realmcrafterorigins_skeletalanimation_master_lib_assimp_code_ms3d_ms3dloader_cpp", "target": "ms3d_ms3dloader_internreadfile", "relation": "contains", "confidence": "EXTRACTED", "source_file": "D:\\Github\\RealmCrafterOrigins\\SkeletalAnimation-master\\lib\\assimp\\code\\MS3D\\MS3DLoader.cpp", "source_location": "L215", "weight": 1.0}, {"source": "ms3d_ms3dloader_internreadfile", "target": "ms3d_ms3dloader_readvector", "relation": "calls", "context": "call", "confidence": "EXTRACTED", "source_file": "D:\\Github\\RealmCrafterOrigins\\SkeletalAnimation-master\\lib\\assimp\\code\\MS3D\\MS3DLoader.cpp", "source_location": "L247", "weight": 1.0}, {"source": "ms3d_ms3dloader_internreadfile", "target": "ms3d_ms3dloader_readcolor", "relation": "calls", "context": "call", "confidence": "EXTRACTED", "source_file": "D:\\Github\\RealmCrafterOrigins\\SkeletalAnimation-master\\lib\\assimp\\code\\MS3D\\MS3DLoader.cpp", "source_location": "L318", "weight": 1.0}, {"source": "ms3d_ms3dloader_internreadfile", "target": "ms3d_ms3dloader_inrange", "relation": "calls", "context": "call", "confidence": "EXTRACTED", "source_file": "D:\\Github\\RealmCrafterOrigins\\SkeletalAnimation-master\\lib\\assimp\\code\\MS3D\\MS3DLoader.cpp", "source_location": "L388", "weight": 1.0}, {"source": "ms3d_ms3dloader_internreadfile", "target": "ms3d_ms3dloader_collectchildjoints", "relation": "calls", "context": "call", "confidence": "EXTRACTED", "source_file": "D:\\Github\\RealmCrafterOrigins\\SkeletalAnimation-master\\lib\\assimp\\code\\MS3D\\MS3DLoader.cpp", "source_location": "L610", "weight": 1.0}], "raw_calls": [{"caller_nid": "ms3d_ms3dloader_canread", "callee": "GetExtension", "is_member_call": false, "source_file": "D:\\Github\\RealmCrafterOrigins\\SkeletalAnimation-master\\lib\\assimp\\code\\MS3D\\MS3DLoader.cpp", "source_location": "L97"}, {"caller_nid": "ms3d_ms3dloader_canread", "callee": "length", "is_member_call": true, "source_file": "D:\\Github\\RealmCrafterOrigins\\SkeletalAnimation-master\\lib\\assimp\\code\\MS3D\\MS3DLoader.cpp", "source_location": "L103"}, {"caller_nid": "ms3d_ms3dloader_canread", "callee": "SearchFileHeaderForToken", "is_member_call": false, "source_file": "D:\\Github\\RealmCrafterOrigins\\SkeletalAnimation-master\\lib\\assimp\\code\\MS3D\\MS3DLoader.cpp", "source_location": "L108"}, {"caller_nid": "ms3d_ms3dloader_readcomments", "callee": "size", "is_member_call": true, "source_file": "D:\\Github\\RealmCrafterOrigins\\SkeletalAnimation-master\\lib\\assimp\\code\\MS3D\\MS3DLoader.cpp", "source_location": "L144"}, {"caller_nid": "ms3d_ms3dloader_readcomments", "callee": "ASSIMP_LOG_WARN", "is_member_call": false, "source_file": "D:\\Github\\RealmCrafterOrigins\\SkeletalAnimation-master\\lib\\assimp\\code\\MS3D\\MS3DLoader.cpp", "source_location": "L145"}, {"caller_nid": "ms3d_ms3dloader_readcomments", "callee": "GetRemainingSize", "is_member_call": true, "source_file": "D:\\Github\\RealmCrafterOrigins\\SkeletalAnimation-master\\lib\\assimp\\code\\MS3D\\MS3DLoader.cpp", "source_location": "L147"}, {"caller_nid": "ms3d_ms3dloader_readcomments", "callee": "DeadlyImportError", "is_member_call": false, "source_file": "D:\\Github\\RealmCrafterOrigins\\SkeletalAnimation-master\\lib\\assimp\\code\\MS3D\\MS3DLoader.cpp", "source_location": "L148"}, {"caller_nid": "ms3d_ms3dloader_readcomments", "callee": "string", "is_member_call": true, "source_file": "D:\\Github\\RealmCrafterOrigins\\SkeletalAnimation-master\\lib\\assimp\\code\\MS3D\\MS3DLoader.cpp", "source_location": "L151"}, {"caller_nid": "ms3d_ms3dloader_readcomments", "callee": "GetPtr", "is_member_call": true, "source_file": "D:\\Github\\RealmCrafterOrigins\\SkeletalAnimation-master\\lib\\assimp\\code\\MS3D\\MS3DLoader.cpp", "source_location": "L151"}, {"caller_nid": "ms3d_ms3dloader_readcomments", "callee": "IncPtr", "is_member_call": true, "source_file": "D:\\Github\\RealmCrafterOrigins\\SkeletalAnimation-master\\lib\\assimp\\code\\MS3D\\MS3DLoader.cpp", "source_location": "L153"}, {"caller_nid": "ms3d_ms3dloader_collectchildjoints", "callee": "size", "is_member_call": true, "source_file": "D:\\Github\\RealmCrafterOrigins\\SkeletalAnimation-master\\lib\\assimp\\code\\MS3D\\MS3DLoader.cpp", "source_location": "L170"}, {"caller_nid": "ms3d_ms3dloader_collectchildjoints", "callee": "strcmp", "is_member_call": false, "source_file": "D:\\Github\\RealmCrafterOrigins\\SkeletalAnimation-master\\lib\\assimp\\code\\MS3D\\MS3DLoader.cpp", "source_location": "L171"}, {"caller_nid": "ms3d_ms3dloader_collectchildjoints", "callee": "size", "is_member_call": true, "source_file": "D:\\Github\\RealmCrafterOrigins\\SkeletalAnimation-master\\lib\\assimp\\code\\MS3D\\MS3DLoader.cpp", "source_location": "L178"}, {"caller_nid": "ms3d_ms3dloader_collectchildjoints", "callee": "strcmp", "is_member_call": false, "source_file": "D:\\Github\\RealmCrafterOrigins\\SkeletalAnimation-master\\lib\\assimp\\code\\MS3D\\MS3DLoader.cpp", "source_location": "L179"}, {"caller_nid": "ms3d_ms3dloader_collectchildjoints", "callee": "Translation", "is_member_call": true, "source_file": "D:\\Github\\RealmCrafterOrigins\\SkeletalAnimation-master\\lib\\assimp\\code\\MS3D\\MS3DLoader.cpp", "source_location": "L183"}, {"caller_nid": "ms3d_ms3dloader_collectchildjoints", "callee": "aiMatrix4x4", "is_member_call": false, "source_file": "D:\\Github\\RealmCrafterOrigins\\SkeletalAnimation-master\\lib\\assimp\\code\\MS3D\\MS3DLoader.cpp", "source_location": "L183"}, {"caller_nid": "ms3d_ms3dloader_collectchildjoints", "callee": "aiMatrix4x4", "is_member_call": false, "source_file": "D:\\Github\\RealmCrafterOrigins\\SkeletalAnimation-master\\lib\\assimp\\code\\MS3D\\MS3DLoader.cpp", "source_location": "L183"}, {"caller_nid": "ms3d_ms3dloader_collectchildjoints", "callee": "FromEulerAnglesXYZ", "is_member_call": true, "source_file": "D:\\Github\\RealmCrafterOrigins\\SkeletalAnimation-master\\lib\\assimp\\code\\MS3D\\MS3DLoader.cpp", "source_location": "L184"}, {"caller_nid": "ms3d_ms3dloader_collectchildjoints", "callee": "aiMatrix4x4", "is_member_call": false, "source_file": "D:\\Github\\RealmCrafterOrigins\\SkeletalAnimation-master\\lib\\assimp\\code\\MS3D\\MS3DLoader.cpp", "source_location": "L184"}, {"caller_nid": "ms3d_ms3dloader_collectchildjoints", "callee": "Inverse", "is_member_call": true, "source_file": "D:\\Github\\RealmCrafterOrigins\\SkeletalAnimation-master\\lib\\assimp\\code\\MS3D\\MS3DLoader.cpp", "source_location": "L193"}, {"caller_nid": "ms3d_ms3dloader_collectchildjoints", "callee": "aiMatrix4x4", "is_member_call": false, "source_file": "D:\\Github\\RealmCrafterOrigins\\SkeletalAnimation-master\\lib\\assimp\\code\\MS3D\\MS3DLoader.cpp", "source_location": "L193"}, {"caller_nid": "ms3d_ms3dloader_collectchildjoints", "callee": "size", "is_member_call": true, "source_file": "D:\\Github\\RealmCrafterOrigins\\SkeletalAnimation-master\\lib\\assimp\\code\\MS3D\\MS3DLoader.cpp", "source_location": "L207"}, {"caller_nid": "ms3d_ms3dloader_internreadfile", "callee": "Open", "is_member_call": true, "source_file": "D:\\Github\\RealmCrafterOrigins\\SkeletalAnimation-master\\lib\\assimp\\code\\MS3D\\MS3DLoader.cpp", "source_location": "L218"}, {"caller_nid": "ms3d_ms3dloader_internreadfile", "callee": "CopyAndAdvance", "is_member_call": true, "source_file": "D:\\Github\\RealmCrafterOrigins\\SkeletalAnimation-master\\lib\\assimp\\code\\MS3D\\MS3DLoader.cpp", "source_location": "L229"}, {"caller_nid": "ms3d_ms3dloader_internreadfile", "callee": "strncmp", "is_member_call": false, "source_file": "D:\\Github\\RealmCrafterOrigins\\SkeletalAnimation-master\\lib\\assimp\\code\\MS3D\\MS3DLoader.cpp", "source_location": "L231"}, {"caller_nid": "ms3d_ms3dloader_internreadfile", "callee": "DeadlyImportError", "is_member_call": false, "source_file": "D:\\Github\\RealmCrafterOrigins\\SkeletalAnimation-master\\lib\\assimp\\code\\MS3D\\MS3DLoader.cpp", "source_location": "L232"}, {"caller_nid": "ms3d_ms3dloader_internreadfile", "callee": "DeadlyImportError", "is_member_call": false, "source_file": "D:\\Github\\RealmCrafterOrigins\\SkeletalAnimation-master\\lib\\assimp\\code\\MS3D\\MS3DLoader.cpp", "source_location": "L236"}, {"caller_nid": "ms3d_ms3dloader_internreadfile", "callee": "IncPtr", "is_member_call": true, "source_file": "D:\\Github\\RealmCrafterOrigins\\SkeletalAnimation-master\\lib\\assimp\\code\\MS3D\\MS3DLoader.cpp", "source_location": "L246"}, {"caller_nid": "ms3d_ms3dloader_internreadfile", "callee": "GetI1", "is_member_call": true, "source_file": "D:\\Github\\RealmCrafterOrigins\\SkeletalAnimation-master\\lib\\assimp\\code\\MS3D\\MS3DLoader.cpp", "source_location": "L248"}, {"caller_nid": "ms3d_ms3dloader_internreadfile", "callee": "GetI1", "is_member_call": true, "source_file": "D:\\Github\\RealmCrafterOrigins\\SkeletalAnimation-master\\lib\\assimp\\code\\MS3D\\MS3DLoader.cpp", "source_location": "L249"}, {"caller_nid": "ms3d_ms3dloader_internreadfile", "callee": "IncPtr", "is_member_call": true, "source_file": "D:\\Github\\RealmCrafterOrigins\\SkeletalAnimation-master\\lib\\assimp\\code\\MS3D\\MS3DLoader.cpp", "source_location": "L263"}, {"caller_nid": "ms3d_ms3dloader_internreadfile", "callee": "GetI2", "is_member_call": true, "source_file": "D:\\Github\\RealmCrafterOrigins\\SkeletalAnimation-master\\lib\\assimp\\code\\MS3D\\MS3DLoader.cpp", "source_location": "L265"}, {"caller_nid": "ms3d_ms3dloader_internreadfile", "callee": "GetI1", "is_member_call": true, "source_file": "D:\\Github\\RealmCrafterOrigins\\SkeletalAnimation-master\\lib\\assimp\\code\\MS3D\\MS3DLoader.cpp", "source_location": "L279"}, {"caller_nid": "ms3d_ms3dloader_internreadfile", "callee": "GetI1", "is_member_call": true, "source_file": "D:\\Github\\RealmCrafterOrigins\\SkeletalAnimation-master\\lib\\assimp\\code\\MS3D\\MS3DLoader.cpp", "source_location": "L280"}, {"caller_nid": "ms3d_ms3dloader_internreadfile", "callee": "IncPtr", "is_member_call": true, "source_file": "D:\\Github\\RealmCrafterOrigins\\SkeletalAnimation-master\\lib\\assimp\\code\\MS3D\\MS3DLoader.cpp", "source_location": "L291"}, {"caller_nid": "ms3d_ms3dloader_internreadfile", "callee": "CopyAndAdvance", "is_member_call": true, "source_file": "D:\\Github\\RealmCrafterOrigins\\SkeletalAnimation-master\\lib\\assimp\\code\\MS3D\\MS3DLoader.cpp", "source_location": "L292"}, {"caller_nid": "ms3d_ms3dloader_internreadfile", "callee": "resize", "is_member_call": true, "source_file": "D:\\Github\\RealmCrafterOrigins\\SkeletalAnimation-master\\lib\\assimp\\code\\MS3D\\MS3DLoader.cpp", "source_location": "L298"}, {"caller_nid": "ms3d_ms3dloader_internreadfile", "callee": "GetI2", "is_member_call": true, "source_file": "D:\\Github\\RealmCrafterOrigins\\SkeletalAnimation-master\\lib\\assimp\\code\\MS3D\\MS3DLoader.cpp", "source_location": "L300"}, {"caller_nid": "ms3d_ms3dloader_internreadfile", "callee": "GetI1", "is_member_call": true, "source_file": "D:\\Github\\RealmCrafterOrigins\\SkeletalAnimation-master\\lib\\assimp\\code\\MS3D\\MS3DLoader.cpp", "source_location": "L302"}, {"caller_nid": "ms3d_ms3dloader_internreadfile", "callee": "CopyAndAdvance", "is_member_call": true, "source_file": "D:\\Github\\RealmCrafterOrigins\\SkeletalAnimation-master\\lib\\assimp\\code\\MS3D\\MS3DLoader.cpp", "source_location": "L315"}, {"caller_nid": "ms3d_ms3dloader_internreadfile", "callee": "IncPtr", "is_member_call": true, "source_file": "D:\\Github\\RealmCrafterOrigins\\SkeletalAnimation-master\\lib\\assimp\\code\\MS3D\\MS3DLoader.cpp", "source_location": "L324"}, {"caller_nid": "ms3d_ms3dloader_internreadfile", "callee": "CopyAndAdvance", "is_member_call": true, "source_file": "D:\\Github\\RealmCrafterOrigins\\SkeletalAnimation-master\\lib\\assimp\\code\\MS3D\\MS3DLoader.cpp", "source_location": "L326"}, {"caller_nid": "ms3d_ms3dloader_internreadfile", "callee": "CopyAndAdvance", "is_member_call": true, "source_file": "D:\\Github\\RealmCrafterOrigins\\SkeletalAnimation-master\\lib\\assimp\\code\\MS3D\\MS3DLoader.cpp", "source_location": "L329"}, {"caller_nid": "ms3d_ms3dloader_internreadfile", "callee": "IncPtr", "is_member_call": true, "source_file": "D:\\Github\\RealmCrafterOrigins\\SkeletalAnimation-master\\lib\\assimp\\code\\MS3D\\MS3DLoader.cpp", "source_location": "L344"}, {"caller_nid": "ms3d_ms3dloader_internreadfile", "callee": "CopyAndAdvance", "is_member_call": true, "source_file": "D:\\Github\\RealmCrafterOrigins\\SkeletalAnimation-master\\lib\\assimp\\code\\MS3D\\MS3DLoader.cpp", "source_location": "L345"}, {"caller_nid": "ms3d_ms3dloader_internreadfile", "callee": "CopyAndAdvance", "is_member_call": true, "source_file": "D:\\Github\\RealmCrafterOrigins\\SkeletalAnimation-master\\lib\\assimp\\code\\MS3D\\MS3DLoader.cpp", "source_location": "L348"}, {"caller_nid": "ms3d_ms3dloader_internreadfile", "callee": "resize", "is_member_call": true, "source_file": "D:\\Github\\RealmCrafterOrigins\\SkeletalAnimation-master\\lib\\assimp\\code\\MS3D\\MS3DLoader.cpp", "source_location": "L354"}, {"caller_nid": "ms3d_ms3dloader_internreadfile", "callee": "GetI2", "is_member_call": true, "source_file": "D:\\Github\\RealmCrafterOrigins\\SkeletalAnimation-master\\lib\\assimp\\code\\MS3D\\MS3DLoader.cpp", "source_location": "L354"}, {"caller_nid": "ms3d_ms3dloader_internreadfile", "callee": "resize", "is_member_call": true, "source_file": "D:\\Github\\RealmCrafterOrigins\\SkeletalAnimation-master\\lib\\assimp\\code\\MS3D\\MS3DLoader.cpp", "source_location": "L355"}, {"caller_nid": "ms3d_ms3dloader_internreadfile", "callee": "GetI2", "is_member_call": true, "source_file": "D:\\Github\\RealmCrafterOrigins\\SkeletalAnimation-master\\lib\\assimp\\code\\MS3D\\MS3DLoader.cpp", "source_location": "L355"}, {"caller_nid": "ms3d_ms3dloader_internreadfile", "callee": "size", "is_member_call": true, "source_file": "D:\\Github\\RealmCrafterOrigins\\SkeletalAnimation-master\\lib\\assimp\\code\\MS3D\\MS3DLoader.cpp", "source_location": "L357"}, {"caller_nid": "ms3d_ms3dloader_internreadfile", "callee": "size", "is_member_call": true, "source_file": "D:\\Github\\RealmCrafterOrigins\\SkeletalAnimation-master\\lib\\assimp\\code\\MS3D\\MS3DLoader.cpp", "source_location": "L362"}, {"caller_nid": "ms3d_ms3dloader_internreadfile", "callee": "GetRemainingSize", "is_member_call": true, "source_file": "D:\\Github\\RealmCrafterOrigins\\SkeletalAnimation-master\\lib\\assimp\\code\\MS3D\\MS3DLoader.cpp", "source_location": "L369"}, {"caller_nid": "ms3d_ms3dloader_internreadfile", "callee": "GetI4", "is_member_call": true, "source_file": "D:\\Github\\RealmCrafterOrigins\\SkeletalAnimation-master\\lib\\assimp\\code\\MS3D\\MS3DLoader.cpp", "source_location": "L378"}, {"caller_nid": "ms3d_ms3dloader_internreadfile", "callee": "GetI4", "is_member_call": true, "source_file": "D:\\Github\\RealmCrafterOrigins\\SkeletalAnimation-master\\lib\\assimp\\code\\MS3D\\MS3DLoader.cpp", "source_location": "L379"}, {"caller_nid": "ms3d_ms3dloader_internreadfile", "callee": "GetRemainingSize", "is_member_call": true, "source_file": "D:\\Github\\RealmCrafterOrigins\\SkeletalAnimation-master\\lib\\assimp\\code\\MS3D\\MS3DLoader.cpp", "source_location": "L380"}, {"caller_nid": "ms3d_ms3dloader_internreadfile", "callee": "DeadlyImportError", "is_member_call": false, "source_file": "D:\\Github\\RealmCrafterOrigins\\SkeletalAnimation-master\\lib\\assimp\\code\\MS3D\\MS3DLoader.cpp", "source_location": "L381"}, {"caller_nid": "ms3d_ms3dloader_internreadfile", "callee": "string", "is_member_call": true, "source_file": "D:\\Github\\RealmCrafterOrigins\\SkeletalAnimation-master\\lib\\assimp\\code\\MS3D\\MS3DLoader.cpp", "source_location": "L384"}, {"caller_nid": "ms3d_ms3dloader_internreadfile", "callee": "GetPtr", "is_member_call": true, "source_file": "D:\\Github\\RealmCrafterOrigins\\SkeletalAnimation-master\\lib\\assimp\\code\\MS3D\\MS3DLoader.cpp", "source_location": "L384"}, {"caller_nid": "ms3d_ms3dloader_internreadfile", "callee": "ASSIMP_LOG_DEBUG_F", "is_member_call": false, "source_file": "D:\\Github\\RealmCrafterOrigins\\SkeletalAnimation-master\\lib\\assimp\\code\\MS3D\\MS3DLoader.cpp", "source_location": "L385"}, {"caller_nid": "ms3d_ms3dloader_internreadfile", "callee": "GetRemainingSize", "is_member_call": true, "source_file": "D:\\Github\\RealmCrafterOrigins\\SkeletalAnimation-master\\lib\\assimp\\code\\MS3D\\MS3DLoader.cpp", "source_location": "L388"}, {"caller_nid": "ms3d_ms3dloader_internreadfile", "callee": "GetI1", "is_member_call": true, "source_file": "D:\\Github\\RealmCrafterOrigins\\SkeletalAnimation-master\\lib\\assimp\\code\\MS3D\\MS3DLoader.cpp", "source_location": "L393"}, {"caller_nid": "ms3d_ms3dloader_internreadfile", "callee": "GetI1", "is_member_call": true, "source_file": "D:\\Github\\RealmCrafterOrigins\\SkeletalAnimation-master\\lib\\assimp\\code\\MS3D\\MS3DLoader.cpp", "source_location": "L394"}, {"caller_nid": "ms3d_ms3dloader_internreadfile", "callee": "IncPtr", "is_member_call": true, "source_file": "D:\\Github\\RealmCrafterOrigins\\SkeletalAnimation-master\\lib\\assimp\\code\\MS3D\\MS3DLoader.cpp", "source_location": "L396"}, {"caller_nid": "ms3d_ms3dloader_internreadfile", "callee": "size", "is_member_call": true, "source_file": "D:\\Github\\RealmCrafterOrigins\\SkeletalAnimation-master\\lib\\assimp\\code\\MS3D\\MS3DLoader.cpp", "source_location": "L406"}, {"caller_nid": "ms3d_ms3dloader_internreadfile", "callee": "ASSIMP_LOG_WARN", "is_member_call": false, "source_file": "D:\\Github\\RealmCrafterOrigins\\SkeletalAnimation-master\\lib\\assimp\\code\\MS3D\\MS3DLoader.cpp", "source_location": "L407"}, {"caller_nid": "ms3d_ms3dloader_internreadfile", "callee": "push_back", "is_member_call": true, "source_file": "D:\\Github\\RealmCrafterOrigins\\SkeletalAnimation-master\\lib\\assimp\\code\\MS3D\\MS3DLoader.cpp", "source_location": "L411"}, {"caller_nid": "ms3d_ms3dloader_internreadfile", "callee": "TempMaterial", "is_member_call": false, "source_file": "D:\\Github\\RealmCrafterOrigins\\SkeletalAnimation-master\\lib\\assimp\\code\\MS3D\\MS3DLoader.cpp", "source_location": "L411"}, {"caller_nid": "ms3d_ms3dloader_internreadfile", "callee": "back", "is_member_call": true, "source_file": "D:\\Github\\RealmCrafterOrigins\\SkeletalAnimation-master\\lib\\assimp\\code\\MS3D\\MS3DLoader.cpp", "source_location": "L412"}, {"caller_nid": "ms3d_ms3dloader_internreadfile", "callee": "strcpy", "is_member_call": false, "source_file": "D:\\Github\\RealmCrafterOrigins\\SkeletalAnimation-master\\lib\\assimp\\code\\MS3D\\MS3DLoader.cpp", "source_location": "L414"}, {"caller_nid": "ms3d_ms3dloader_internreadfile", "callee": "aiColor4D", "is_member_call": false, "source_file": "D:\\Github\\RealmCrafterOrigins\\SkeletalAnimation-master\\lib\\assimp\\code\\MS3D\\MS3DLoader.cpp", "source_location": "L415"}, {"caller_nid": "ms3d_ms3dloader_internreadfile", "callee": "size", "is_member_call": true, "source_file": "D:\\Github\\RealmCrafterOrigins\\SkeletalAnimation-master\\lib\\assimp\\code\\MS3D\\MS3DLoader.cpp", "source_location": "L422"}, {"caller_nid": "ms3d_ms3dloader_internreadfile", "callee": "size", "is_member_call": true, "source_file": "D:\\Github\\RealmCrafterOrigins\\SkeletalAnimation-master\\lib\\assimp\\code\\MS3D\\MS3DLoader.cpp", "source_location": "L425"}, {"caller_nid": "ms3d_ms3dloader_internreadfile", "callee": "size", "is_member_call": true, "source_file": "D:\\Github\\RealmCrafterOrigins\\SkeletalAnimation-master\\lib\\assimp\\code\\MS3D\\MS3DLoader.cpp", "source_location": "L431"}, {"caller_nid": "ms3d_ms3dloader_internreadfile", "callee": "size", "is_member_call": true, "source_file": "D:\\Github\\RealmCrafterOrigins\\SkeletalAnimation-master\\lib\\assimp\\code\\MS3D\\MS3DLoader.cpp", "source_location": "L432"}, {"caller_nid": "ms3d_ms3dloader_internreadfile", "callee": "size", "is_member_call": true, "source_file": "D:\\Github\\RealmCrafterOrigins\\SkeletalAnimation-master\\lib\\assimp\\code\\MS3D\\MS3DLoader.cpp", "source_location": "L433"}, {"caller_nid": "ms3d_ms3dloader_internreadfile", "callee": "aiString", "is_member_call": false, "source_file": "D:\\Github\\RealmCrafterOrigins\\SkeletalAnimation-master\\lib\\assimp\\code\\MS3D\\MS3DLoader.cpp", "source_location": "L442"}, {"caller_nid": "ms3d_ms3dloader_internreadfile", "callee": "AddProperty", "is_member_call": true, "source_file": "D:\\Github\\RealmCrafterOrigins\\SkeletalAnimation-master\\lib\\assimp\\code\\MS3D\\MS3DLoader.cpp", "source_location": "L443"}, {"caller_nid": "ms3d_ms3dloader_internreadfile", "callee": "AI_MATKEY_TEXTURE_OPACITY", "is_member_call": false, "source_file": "D:\\Github\\RealmCrafterOrigins\\SkeletalAnimation-master\\lib\\assimp\\code\\MS3D\\MS3DLoader.cpp", "source_location": "L443"}, {"caller_nid": "ms3d_ms3dloader_internreadfile", "callee": "aiString", "is_member_call": false, "source_file": "D:\\Github\\RealmCrafterOrigins\\SkeletalAnimation-master\\lib\\assimp\\code\\MS3D\\MS3DLoader.cpp", "source_location": "L446"}, {"caller_nid": "ms3d_ms3dloader_internreadfile", "callee": "AddProperty", "is_member_call": true, "source_file": "D:\\Github\\RealmCrafterOrigins\\SkeletalAnimation-master\\lib\\assimp\\code\\MS3D\\MS3DLoader.cpp", "source_location": "L447"}, {"caller_nid": "ms3d_ms3dloader_internreadfile", "callee": "AI_MATKEY_TEXTURE_DIFFUSE", "is_member_call": false, "source_file": "D:\\Github\\RealmCrafterOrigins\\SkeletalAnimation-master\\lib\\assimp\\code\\MS3D\\MS3DLoader.cpp", "source_location": "L447"}, {"caller_nid": "ms3d_ms3dloader_internreadfile", "callee": "aiString", "is_member_call": false, "source_file": "D:\\Github\\RealmCrafterOrigins\\SkeletalAnimation-master\\lib\\assimp\\code\\MS3D\\MS3DLoader.cpp", "source_location": "L450"}, {"caller_nid": "ms3d_ms3dloader_internreadfile", "callee": "AddProperty", "is_member_call": true, "source_file": "D:\\Github\\RealmCrafterOrigins\\SkeletalAnimation-master\\lib\\assimp\\code\\MS3D\\MS3DLoader.cpp", "source_location": "L451"}, {"caller_nid": "ms3d_ms3dloader_internreadfile", "callee": "AddProperty", "is_member_call": true, "source_file": "D:\\Github\\RealmCrafterOrigins\\SkeletalAnimation-master\\lib\\assimp\\code\\MS3D\\MS3DLoader.cpp", "source_location": "L454"}, {"caller_nid": "ms3d_ms3dloader_internreadfile", "callee": "AddProperty", "is_member_call": true, "source_file": "D:\\Github\\RealmCrafterOrigins\\SkeletalAnimation-master\\lib\\assimp\\code\\MS3D\\MS3DLoader.cpp", "source_location": "L455"}, {"caller_nid": "ms3d_ms3dloader_internreadfile", "callee": "AddProperty", "is_member_call": true, "source_file": "D:\\Github\\RealmCrafterOrigins\\SkeletalAnimation-master\\lib\\assimp\\code\\MS3D\\MS3DLoader.cpp", "source_location": "L456"}, {"caller_nid": "ms3d_ms3dloader_internreadfile", "callee": "AddProperty", "is_member_call": true, "source_file": "D:\\Github\\RealmCrafterOrigins\\SkeletalAnimation-master\\lib\\assimp\\code\\MS3D\\MS3DLoader.cpp", "source_location": "L457"}, {"caller_nid": "ms3d_ms3dloader_internreadfile", "callee": "AddProperty", "is_member_call": true, "source_file": "D:\\Github\\RealmCrafterOrigins\\SkeletalAnimation-master\\lib\\assimp\\code\\MS3D\\MS3DLoader.cpp", "source_location": "L459"}, {"caller_nid": "ms3d_ms3dloader_internreadfile", "callee": "AddProperty", "is_member_call": true, "source_file": "D:\\Github\\RealmCrafterOrigins\\SkeletalAnimation-master\\lib\\assimp\\code\\MS3D\\MS3DLoader.cpp", "source_location": "L460"}, {"caller_nid": "ms3d_ms3dloader_internreadfile", "callee": "AddProperty", "is_member_call": true, "source_file": "D:\\Github\\RealmCrafterOrigins\\SkeletalAnimation-master\\lib\\assimp\\code\\MS3D\\MS3DLoader.cpp", "source_location": "L463"}, {"caller_nid": "ms3d_ms3dloader_internreadfile", "callee": "empty", "is_member_call": true, "source_file": "D:\\Github\\RealmCrafterOrigins\\SkeletalAnimation-master\\lib\\assimp\\code\\MS3D\\MS3DLoader.cpp", "source_location": "L468"}, {"caller_nid": "ms3d_ms3dloader_internreadfile", "callee": "DeadlyImportError", "is_member_call": false, "source_file": "D:\\Github\\RealmCrafterOrigins\\SkeletalAnimation-master\\lib\\assimp\\code\\MS3D\\MS3DLoader.cpp", "source_location": "L469"}, {"caller_nid": "ms3d_ms3dloader_internreadfile", "callee": "size", "is_member_call": true, "source_file": "D:\\Github\\RealmCrafterOrigins\\SkeletalAnimation-master\\lib\\assimp\\code\\MS3D\\MS3DLoader.cpp", "source_location": "L472"}, {"caller_nid": "ms3d_ms3dloader_internreadfile", "callee": "DeadlyImportError", "is_member_call": false, "source_file": "D:\\Github\\RealmCrafterOrigins\\SkeletalAnimation-master\\lib\\assimp\\code\\MS3D\\MS3DLoader.cpp", "source_location": "L479"}, {"caller_nid": "ms3d_ms3dloader_internreadfile", "callee": "size", "is_member_call": true, "source_file": "D:\\Github\\RealmCrafterOrigins\\SkeletalAnimation-master\\lib\\assimp\\code\\MS3D\\MS3DLoader.cpp", "source_location": "L485"}, {"caller_nid": "ms3d_ms3dloader_internreadfile", "callee": "size", "is_member_call": true, "source_file": "D:\\Github\\RealmCrafterOrigins\\SkeletalAnimation-master\\lib\\assimp\\code\\MS3D\\MS3DLoader.cpp", "source_location": "L499"}, {"caller_nid": "ms3d_ms3dloader_internreadfile", "callee": "DeadlyImportError", "is_member_call": false, "source_file": "D:\\Github\\RealmCrafterOrigins\\SkeletalAnimation-master\\lib\\assimp\\code\\MS3D\\MS3DLoader.cpp", "source_location": "L500"}, {"caller_nid": "ms3d_ms3dloader_internreadfile", "callee": "size", "is_member_call": true, "source_file": "D:\\Github\\RealmCrafterOrigins\\SkeletalAnimation-master\\lib\\assimp\\code\\MS3D\\MS3DLoader.cpp", "source_location": "L507"}, {"caller_nid": "ms3d_ms3dloader_internreadfile", "callee": "DeadlyImportError", "is_member_call": false, "source_file": "D:\\Github\\RealmCrafterOrigins\\SkeletalAnimation-master\\lib\\assimp\\code\\MS3D\\MS3DLoader.cpp", "source_location": "L508"}, {"caller_nid": "ms3d_ms3dloader_internreadfile", "callee": "size", "is_member_call": true, "source_file": "D:\\Github\\RealmCrafterOrigins\\SkeletalAnimation-master\\lib\\assimp\\code\\MS3D\\MS3DLoader.cpp", "source_location": "L514"}, {"caller_nid": "ms3d_ms3dloader_internreadfile", "callee": "DeadlyImportError", "is_member_call": false, "source_file": "D:\\Github\\RealmCrafterOrigins\\SkeletalAnimation-master\\lib\\assimp\\code\\MS3D\\MS3DLoader.cpp", "source_location": "L515"}, {"caller_nid": "ms3d_ms3dloader_internreadfile", "callee": "find", "is_member_call": true, "source_file": "D:\\Github\\RealmCrafterOrigins\\SkeletalAnimation-master\\lib\\assimp\\code\\MS3D\\MS3DLoader.cpp", "source_location": "L517"}, {"caller_nid": "ms3d_ms3dloader_internreadfile", "callee": "end", "is_member_call": true, "source_file": "D:\\Github\\RealmCrafterOrigins\\SkeletalAnimation-master\\lib\\assimp\\code\\MS3D\\MS3DLoader.cpp", "source_location": "L517"}, {"caller_nid": "ms3d_ms3dloader_internreadfile", "callee": "aiVector3D", "is_member_call": false, "source_file": "D:\\Github\\RealmCrafterOrigins\\SkeletalAnimation-master\\lib\\assimp\\code\\MS3D\\MS3DLoader.cpp", "source_location": "L528"}, {"caller_nid": "ms3d_ms3dloader_internreadfile", "callee": "empty", "is_member_call": true, "source_file": "D:\\Github\\RealmCrafterOrigins\\SkeletalAnimation-master\\lib\\assimp\\code\\MS3D\\MS3DLoader.cpp", "source_location": "L534"}, {"caller_nid": "ms3d_ms3dloader_internreadfile", "callee": "size", "is_member_call": true, "source_file": "D:\\Github\\RealmCrafterOrigins\\SkeletalAnimation-master\\lib\\assimp\\code\\MS3D\\MS3DLoader.cpp", "source_location": "L535"}, {"caller_nid": "ms3d_ms3dloader_internreadfile", "callee": "size", "is_member_call": true, "source_file": "D:\\Github\\RealmCrafterOrigins\\SkeletalAnimation-master\\lib\\assimp\\code\\MS3D\\MS3DLoader.cpp", "source_location": "L536"}, {"caller_nid": "ms3d_ms3dloader_internreadfile", "callee": "begin", "is_member_call": true, "source_file": "D:\\Github\\RealmCrafterOrigins\\SkeletalAnimation-master\\lib\\assimp\\code\\MS3D\\MS3DLoader.cpp", "source_location": "L537"}, {"caller_nid": "ms3d_ms3dloader_internreadfile", "callee": "end", "is_member_call": true, "source_file": "D:\\Github\\RealmCrafterOrigins\\SkeletalAnimation-master\\lib\\assimp\\code\\MS3D\\MS3DLoader.cpp", "source_location": "L537"}, {"caller_nid": "ms3d_ms3dloader_internreadfile", "callee": "Set", "is_member_call": true, "source_file": "D:\\Github\\RealmCrafterOrigins\\SkeletalAnimation-master\\lib\\assimp\\code\\MS3D\\MS3DLoader.cpp", "source_location": "L541"}, {"caller_nid": "ms3d_ms3dloader_internreadfile", "callee": "size", "is_member_call": true, "source_file": "D:\\Github\\RealmCrafterOrigins\\SkeletalAnimation-master\\lib\\assimp\\code\\MS3D\\MS3DLoader.cpp", "source_location": "L575"}, {"caller_nid": "ms3d_ms3dloader_internreadfile", "callee": "aiString", "is_member_call": false, "source_file": "D:\\Github\\RealmCrafterOrigins\\SkeletalAnimation-master\\lib\\assimp\\code\\MS3D\\MS3DLoader.cpp", "source_location": "L585"}, {"caller_nid": "ms3d_ms3dloader_internreadfile", "callee": "Append", "is_member_call": true, "source_file": "D:\\Github\\RealmCrafterOrigins\\SkeletalAnimation-master\\lib\\assimp\\code\\MS3D\\MS3DLoader.cpp", "source_location": "L586"}, {"caller_nid": "ms3d_ms3dloader_internreadfile", "callee": "size", "is_member_call": true, "source_file": "D:\\Github\\RealmCrafterOrigins\\SkeletalAnimation-master\\lib\\assimp\\code\\MS3D\\MS3DLoader.cpp", "source_location": "L600"}, {"caller_nid": "ms3d_ms3dloader_internreadfile", "callee": "Set", "is_member_call": true, "source_file": "D:\\Github\\RealmCrafterOrigins\\SkeletalAnimation-master\\lib\\assimp\\code\\MS3D\\MS3DLoader.cpp", "source_location": "L611"}, {"caller_nid": "ms3d_ms3dloader_internreadfile", "callee": "Set", "is_member_call": true, "source_file": "D:\\Github\\RealmCrafterOrigins\\SkeletalAnimation-master\\lib\\assimp\\code\\MS3D\\MS3DLoader.cpp", "source_location": "L616"}, {"caller_nid": "ms3d_ms3dloader_internreadfile", "callee": "size", "is_member_call": true, "source_file": "D:\\Github\\RealmCrafterOrigins\\SkeletalAnimation-master\\lib\\assimp\\code\\MS3D\\MS3DLoader.cpp", "source_location": "L626"}, {"caller_nid": "ms3d_ms3dloader_internreadfile", "callee": "begin", "is_member_call": true, "source_file": "D:\\Github\\RealmCrafterOrigins\\SkeletalAnimation-master\\lib\\assimp\\code\\MS3D\\MS3DLoader.cpp", "source_location": "L627"}, {"caller_nid": "ms3d_ms3dloader_internreadfile", "callee": "end", "is_member_call": true, "source_file": "D:\\Github\\RealmCrafterOrigins\\SkeletalAnimation-master\\lib\\assimp\\code\\MS3D\\MS3DLoader.cpp", "source_location": "L627"}, {"caller_nid": "ms3d_ms3dloader_internreadfile", "callee": "empty", "is_member_call": true, "source_file": "D:\\Github\\RealmCrafterOrigins\\SkeletalAnimation-master\\lib\\assimp\\code\\MS3D\\MS3DLoader.cpp", "source_location": "L628"}, {"caller_nid": "ms3d_ms3dloader_internreadfile", "callee": "empty", "is_member_call": true, "source_file": "D:\\Github\\RealmCrafterOrigins\\SkeletalAnimation-master\\lib\\assimp\\code\\MS3D\\MS3DLoader.cpp", "source_location": "L628"}, {"caller_nid": "ms3d_ms3dloader_internreadfile", "callee": "Set", "is_member_call": true, "source_file": "D:\\Github\\RealmCrafterOrigins\\SkeletalAnimation-master\\lib\\assimp\\code\\MS3D\\MS3DLoader.cpp", "source_location": "L633"}, {"caller_nid": "ms3d_ms3dloader_internreadfile", "callee": "size", "is_member_call": true, "source_file": "D:\\Github\\RealmCrafterOrigins\\SkeletalAnimation-master\\lib\\assimp\\code\\MS3D\\MS3DLoader.cpp", "source_location": "L635"}, {"caller_nid": "ms3d_ms3dloader_internreadfile", "callee": "size", "is_member_call": true, "source_file": "D:\\Github\\RealmCrafterOrigins\\SkeletalAnimation-master\\lib\\assimp\\code\\MS3D\\MS3DLoader.cpp", "source_location": "L636"}, {"caller_nid": "ms3d_ms3dloader_internreadfile", "callee": "begin", "is_member_call": true, "source_file": "D:\\Github\\RealmCrafterOrigins\\SkeletalAnimation-master\\lib\\assimp\\code\\MS3D\\MS3DLoader.cpp", "source_location": "L637"}, {"caller_nid": "ms3d_ms3dloader_internreadfile", "callee": "end", "is_member_call": true, "source_file": "D:\\Github\\RealmCrafterOrigins\\SkeletalAnimation-master\\lib\\assimp\\code\\MS3D\\MS3DLoader.cpp", "source_location": "L637"}, {"caller_nid": "ms3d_ms3dloader_internreadfile", "callee": "aiQuaternion", "is_member_call": false, "source_file": "D:\\Github\\RealmCrafterOrigins\\SkeletalAnimation-master\\lib\\assimp\\code\\MS3D\\MS3DLoader.cpp", "source_location": "L641"}, {"caller_nid": "ms3d_ms3dloader_internreadfile", "callee": "aiMatrix3x3", "is_member_call": false, "source_file": "D:\\Github\\RealmCrafterOrigins\\SkeletalAnimation-master\\lib\\assimp\\code\\MS3D\\MS3DLoader.cpp", "source_location": "L641"}, {"caller_nid": "ms3d_ms3dloader_internreadfile", "callee": "FromEulerAnglesXYZ", "is_member_call": true, "source_file": "D:\\Github\\RealmCrafterOrigins\\SkeletalAnimation-master\\lib\\assimp\\code\\MS3D\\MS3DLoader.cpp", "source_location": "L641"}, {"caller_nid": "ms3d_ms3dloader_internreadfile", "callee": "aiMatrix4x4", "is_member_call": false, "source_file": "D:\\Github\\RealmCrafterOrigins\\SkeletalAnimation-master\\lib\\assimp\\code\\MS3D\\MS3DLoader.cpp", "source_location": "L641"}, {"caller_nid": "ms3d_ms3dloader_internreadfile", "callee": "FromEulerAnglesXYZ", "is_member_call": true, "source_file": "D:\\Github\\RealmCrafterOrigins\\SkeletalAnimation-master\\lib\\assimp\\code\\MS3D\\MS3DLoader.cpp", "source_location": "L642"}, {"caller_nid": "ms3d_ms3dloader_internreadfile", "callee": "aiMatrix4x4", "is_member_call": false, "source_file": "D:\\Github\\RealmCrafterOrigins\\SkeletalAnimation-master\\lib\\assimp\\code\\MS3D\\MS3DLoader.cpp", "source_location": "L642"}, {"caller_nid": "ms3d_ms3dloader_internreadfile", "callee": "size", "is_member_call": true, "source_file": "D:\\Github\\RealmCrafterOrigins\\SkeletalAnimation-master\\lib\\assimp\\code\\MS3D\\MS3DLoader.cpp", "source_location": "L646"}, {"caller_nid": "ms3d_ms3dloader_internreadfile", "callee": "size", "is_member_call": true, "source_file": "D:\\Github\\RealmCrafterOrigins\\SkeletalAnimation-master\\lib\\assimp\\code\\MS3D\\MS3DLoader.cpp", "source_location": "L647"}, {"caller_nid": "ms3d_ms3dloader_internreadfile", "callee": "begin", "is_member_call": true, "source_file": "D:\\Github\\RealmCrafterOrigins\\SkeletalAnimation-master\\lib\\assimp\\code\\MS3D\\MS3DLoader.cpp", "source_location": "L650"}, {"caller_nid": "ms3d_ms3dloader_internreadfile", "callee": "end", "is_member_call": true, "source_file": "D:\\Github\\RealmCrafterOrigins\\SkeletalAnimation-master\\lib\\assimp\\code\\MS3D\\MS3DLoader.cpp", "source_location": "L650"}]}