{"nodes": [{"id": "d_github_realmcrafterorigins_skeletalanimation_master_lib_glfw_src_init_c", "label": "init.c", "file_type": "code", "source_file": "D:\\Github\\RealmCrafterOrigins\\SkeletalAnimation-master\\lib\\glfw\\src\\init.c", "source_location": "L1"}, {"id": "src_init_terminate", "label": "terminate()", "file_type": "code", "source_file": "D:\\Github\\RealmCrafterOrigins\\SkeletalAnimation-master\\lib\\glfw\\src\\init.c", "source_location": "L65"}, {"id": "src_init_glfw_strdup", "label": "_glfw_strdup()", "file_type": "code", "source_file": "D:\\Github\\RealmCrafterOrigins\\SkeletalAnimation-master\\lib\\glfw\\src\\init.c", "source_location": "L118"}, {"id": "src_init_glfw_fminf", "label": "_glfw_fminf()", "file_type": "code", "source_file": "D:\\Github\\RealmCrafterOrigins\\SkeletalAnimation-master\\lib\\glfw\\src\\init.c", "source_location": "L126"}, {"id": "src_init_glfw_fmaxf", "label": "_glfw_fmaxf()", "file_type": "code", "source_file": "D:\\Github\\RealmCrafterOrigins\\SkeletalAnimation-master\\lib\\glfw\\src\\init.c", "source_location": "L138"}, {"id": "src_init_glfwinputerror", "label": "_glfwInputError()", "file_type": "code", "source_file": "D:\\Github\\RealmCrafterOrigins\\SkeletalAnimation-master\\lib\\glfw\\src\\init.c", "source_location": "L157"}, {"id": "src_init_glfwinit", "label": "glfwInit()", "file_type": "code", "source_file": "D:\\Github\\RealmCrafterOrigins\\SkeletalAnimation-master\\lib\\glfw\\src\\init.c", "source_location": "L232"}, {"id": "src_init_glfwterminate", "label": "glfwTerminate()", "file_type": "code", "source_file": "D:\\Github\\RealmCrafterOrigins\\SkeletalAnimation-master\\lib\\glfw\\src\\init.c", "source_location": "L277"}, {"id": "src_init_glfwinithint", "label": "glfwInitHint()", "file_type": "code", "source_file": "D:\\Github\\RealmCrafterOrigins\\SkeletalAnimation-master\\lib\\glfw\\src\\init.c", "source_location": "L285"}, {"id": "src_init_glfwgetversion", "label": "glfwGetVersion()", "file_type": "code", "source_file": "D:\\Github\\RealmCrafterOrigins\\SkeletalAnimation-master\\lib\\glfw\\src\\init.c", "source_location": "L307"}, {"id": "src_init_glfwgetversionstring", "label": "glfwGetVersionString()", "file_type": "code", "source_file": "D:\\Github\\RealmCrafterOrigins\\SkeletalAnimation-master\\lib\\glfw\\src\\init.c", "source_location": "L317"}, {"id": "src_init_glfwgeterror", "label": "glfwGetError()", "file_type": "code", "source_file": "D:\\Github\\RealmCrafterOrigins\\SkeletalAnimation-master\\lib\\glfw\\src\\init.c", "source_location": "L322"}, {"id": "src_init_glfwseterrorcallback", "label": "glfwSetErrorCallback()", "file_type": "code", "source_file": "D:\\Github\\RealmCrafterOrigins\\SkeletalAnimation-master\\lib\\glfw\\src\\init.c", "source_location": "L346"}], "edges": [{"source": "d_github_realmcrafterorigins_skeletalanimation_master_lib_glfw_src_init_c", "target": "internal", "relation": "imports", "context": "import", "confidence": "EXTRACTED", "source_file": "D:\\Github\\RealmCrafterOrigins\\SkeletalAnimation-master\\lib\\glfw\\src\\init.c", "source_location": "L30", "weight": 1.0}, {"source": "d_github_realmcrafterorigins_skeletalanimation_master_lib_glfw_src_init_c", "target": "mappings", "relation": "imports", "context": "import", "confidence": "EXTRACTED", "source_file": "D:\\Github\\RealmCrafterOrigins\\SkeletalAnimation-master\\lib\\glfw\\src\\init.c", "source_location": "L31", "weight": 1.0}, {"source": "d_github_realmcrafterorigins_skeletalanimation_master_lib_glfw_src_init_c", "target": "string", "relation": "imports", "context": "import", "confidence": "EXTRACTED", "source_file": "D:\\Github\\RealmCrafterOrigins\\SkeletalAnimation-master\\lib\\glfw\\src\\init.c", "source_location": "L33", "weight": 1.0}, {"source": "d_github_realmcrafterorigins_skeletalanimation_master_lib_glfw_src_init_c", "target": "stdlib", "relation": "imports", "context": "import", "confidence": "EXTRACTED", "source_file": "D:\\Github\\RealmCrafterOrigins\\SkeletalAnimation-master\\lib\\glfw\\src\\init.c", "source_location": "L34", "weight": 1.0}, {"source": "d_github_realmcrafterorigins_skeletalanimation_master_lib_glfw_src_init_c", "target": "stdio", "relation": "imports", "context": "import", "confidence": "EXTRACTED", "source_file": "D:\\Github\\RealmCrafterOrigins\\SkeletalAnimation-master\\lib\\glfw\\src\\init.c", "source_location": "L35", "weight": 1.0}, {"source": "d_github_realmcrafterorigins_skeletalanimation_master_lib_glfw_src_init_c", "target": "stdarg", "relation": "imports", "context": "import", "confidence": "EXTRACTED", "source_file": "D:\\Github\\RealmCrafterOrigins\\SkeletalAnimation-master\\lib\\glfw\\src\\init.c", "source_location": "L36", "weight": 1.0}, {"source": "d_github_realmcrafterorigins_skeletalanimation_master_lib_glfw_src_init_c", "target": "assert", "relation": "imports", "context": "import", "confidence": "EXTRACTED", "source_file": "D:\\Github\\RealmCrafterOrigins\\SkeletalAnimation-master\\lib\\glfw\\src\\init.c", "source_location": "L37", "weight": 1.0}, {"source": "d_github_realmcrafterorigins_skeletalanimation_master_lib_glfw_src_init_c", "target": "src_init_terminate", "relation": "contains", "confidence": "EXTRACTED", "source_file": "D:\\Github\\RealmCrafterOrigins\\SkeletalAnimation-master\\lib\\glfw\\src\\init.c", "source_location": "L65", "weight": 1.0}, {"source": "d_github_realmcrafterorigins_skeletalanimation_master_lib_glfw_src_init_c", "target": "src_init_glfw_strdup", "relation": "contains", "confidence": "EXTRACTED", "source_file": "D:\\Github\\RealmCrafterOrigins\\SkeletalAnimation-master\\lib\\glfw\\src\\init.c", "source_location": "L118", "weight": 1.0}, {"source": "d_github_realmcrafterorigins_skeletalanimation_master_lib_glfw_src_init_c", "target": "src_init_glfw_fminf", "relation": "contains", "confidence": "EXTRACTED", "source_file": "D:\\Github\\RealmCrafterOrigins\\SkeletalAnimation-master\\lib\\glfw\\src\\init.c", "source_location": "L126", "weight": 1.0}, {"source": "d_github_realmcrafterorigins_skeletalanimation_master_lib_glfw_src_init_c", "target": "src_init_glfw_fmaxf", "relation": "contains", "confidence": "EXTRACTED", "source_file": "D:\\Github\\RealmCrafterOrigins\\SkeletalAnimation-master\\lib\\glfw\\src\\init.c", "source_location": "L138", "weight": 1.0}, {"source": "d_github_realmcrafterorigins_skeletalanimation_master_lib_glfw_src_init_c", "target": "src_init_glfwinputerror", "relation": "contains", "confidence": "EXTRACTED", "source_file": "D:\\Github\\RealmCrafterOrigins\\SkeletalAnimation-master\\lib\\glfw\\src\\init.c", "source_location": "L157", "weight": 1.0}, {"source": "d_github_realmcrafterorigins_skeletalanimation_master_lib_glfw_src_init_c", "target": "src_init_glfwinit", "relation": "contains", "confidence": "EXTRACTED", "source_file": "D:\\Github\\RealmCrafterOrigins\\SkeletalAnimation-master\\lib\\glfw\\src\\init.c", "source_location": "L232", "weight": 1.0}, {"source": "d_github_realmcrafterorigins_skeletalanimation_master_lib_glfw_src_init_c", "target": "src_init_glfwterminate", "relation": "contains", "confidence": "EXTRACTED", "source_file": "D:\\Github\\RealmCrafterOrigins\\SkeletalAnimation-master\\lib\\glfw\\src\\init.c", "source_location": "L277", "weight": 1.0}, {"source": "d_github_realmcrafterorigins_skeletalanimation_master_lib_glfw_src_init_c", "target": "src_init_glfwinithint", "relation": "contains", "confidence": "EXTRACTED", "source_file": "D:\\Github\\RealmCrafterOrigins\\SkeletalAnimation-master\\lib\\glfw\\src\\init.c", "source_location": "L285", "weight": 1.0}, {"source": "d_github_realmcrafterorigins_skeletalanimation_master_lib_glfw_src_init_c", "target": "src_init_glfwgetversion", "relation": "contains", "confidence": "EXTRACTED", "source_file": "D:\\Github\\RealmCrafterOrigins\\SkeletalAnimation-master\\lib\\glfw\\src\\init.c", "source_location": "L307", "weight": 1.0}, {"source": "d_github_realmcrafterorigins_skeletalanimation_master_lib_glfw_src_init_c", "target": "src_init_glfwgetversionstring", "relation": "contains", "confidence": "EXTRACTED", "source_file": "D:\\Github\\RealmCrafterOrigins\\SkeletalAnimation-master\\lib\\glfw\\src\\init.c", "source_location": "L317", "weight": 1.0}, {"source": "d_github_realmcrafterorigins_skeletalanimation_master_lib_glfw_src_init_c", "target": "src_init_glfwgeterror", "relation": "contains", "confidence": "EXTRACTED", "source_file": "D:\\Github\\RealmCrafterOrigins\\SkeletalAnimation-master\\lib\\glfw\\src\\init.c", "source_location": "L322", "weight": 1.0}, {"source": "d_github_realmcrafterorigins_skeletalanimation_master_lib_glfw_src_init_c", "target": "src_init_glfwseterrorcallback", "relation": "contains", "confidence": "EXTRACTED", "source_file": "D:\\Github\\RealmCrafterOrigins\\SkeletalAnimation-master\\lib\\glfw\\src\\init.c", "source_location": "L346", "weight": 1.0}, {"source": "src_init_glfwinit", "target": "src_init_terminate", "relation": "calls", "context": "call", "confidence": "EXTRACTED", "source_file": "D:\\Github\\RealmCrafterOrigins\\SkeletalAnimation-master\\lib\\glfw\\src\\init.c", "source_location": "L242", "weight": 1.0}, {"source": "src_init_glfwterminate", "target": "src_init_terminate", "relation": "calls", "context": "call", "confidence": "EXTRACTED", "source_file": "D:\\Github\\RealmCrafterOrigins\\SkeletalAnimation-master\\lib\\glfw\\src\\init.c", "source_location": "L282", "weight": 1.0}, {"source": "src_init_glfwinithint", "target": "src_init_glfwinputerror", "relation": "calls", "context": "call", "confidence": "EXTRACTED", "source_file": "D:\\Github\\RealmCrafterOrigins\\SkeletalAnimation-master\\lib\\glfw\\src\\init.c", "source_location": "L303", "weight": 1.0}], "raw_calls": [{"caller_nid": "src_init_terminate", "callee": "memset", "is_member_call": false, "source_file": "D:\\Github\\RealmCrafterOrigins\\SkeletalAnimation-master\\lib\\glfw\\src\\init.c", "source_location": "L69"}, {"caller_nid": "src_init_terminate", "callee": "glfwDestroyWindow", "is_member_call": false, "source_file": "D:\\Github\\RealmCrafterOrigins\\SkeletalAnimation-master\\lib\\glfw\\src\\init.c", "source_location": "L72"}, {"caller_nid": "src_init_terminate", "callee": "glfwDestroyCursor", "is_member_call": false, "source_file": "D:\\Github\\RealmCrafterOrigins\\SkeletalAnimation-master\\lib\\glfw\\src\\init.c", "source_location": "L75"}, {"caller_nid": "src_init_terminate", "callee": "_glfwPlatformSetGammaRamp", "is_member_call": false, "source_file": "D:\\Github\\RealmCrafterOrigins\\SkeletalAnimation-master\\lib\\glfw\\src\\init.c", "source_location": "L81"}, {"caller_nid": "src_init_terminate", "callee": "_glfwFreeMonitor", "is_member_call": false, "source_file": "D:\\Github\\RealmCrafterOrigins\\SkeletalAnimation-master\\lib\\glfw\\src\\init.c", "source_location": "L82"}, {"caller_nid": "src_init_terminate", "callee": "free", "is_member_call": false, "source_file": "D:\\Github\\RealmCrafterOrigins\\SkeletalAnimation-master\\lib\\glfw\\src\\init.c", "source_location": "L85"}, {"caller_nid": "src_init_terminate", "callee": "free", "is_member_call": false, "source_file": "D:\\Github\\RealmCrafterOrigins\\SkeletalAnimation-master\\lib\\glfw\\src\\init.c", "source_location": "L89"}, {"caller_nid": "src_init_terminate", "callee": "_glfwTerminateVulkan", "is_member_call": false, "source_file": "D:\\Github\\RealmCrafterOrigins\\SkeletalAnimation-master\\lib\\glfw\\src\\init.c", "source_location": "L93"}, {"caller_nid": "src_init_terminate", "callee": "_glfwPlatformTerminateJoysticks", "is_member_call": false, "source_file": "D:\\Github\\RealmCrafterOrigins\\SkeletalAnimation-master\\lib\\glfw\\src\\init.c", "source_location": "L94"}, {"caller_nid": "src_init_terminate", "callee": "_glfwPlatformTerminate", "is_member_call": false, "source_file": "D:\\Github\\RealmCrafterOrigins\\SkeletalAnimation-master\\lib\\glfw\\src\\init.c", "source_location": "L95"}, {"caller_nid": "src_init_terminate", "callee": "free", "is_member_call": false, "source_file": "D:\\Github\\RealmCrafterOrigins\\SkeletalAnimation-master\\lib\\glfw\\src\\init.c", "source_location": "L103"}, {"caller_nid": "src_init_terminate", "callee": "_glfwPlatformDestroyTls", "is_member_call": false, "source_file": "D:\\Github\\RealmCrafterOrigins\\SkeletalAnimation-master\\lib\\glfw\\src\\init.c", "source_location": "L106"}, {"caller_nid": "src_init_terminate", "callee": "_glfwPlatformDestroyTls", "is_member_call": false, "source_file": "D:\\Github\\RealmCrafterOrigins\\SkeletalAnimation-master\\lib\\glfw\\src\\init.c", "source_location": "L107"}, {"caller_nid": "src_init_terminate", "callee": "_glfwPlatformDestroyMutex", "is_member_call": false, "source_file": "D:\\Github\\RealmCrafterOrigins\\SkeletalAnimation-master\\lib\\glfw\\src\\init.c", "source_location": "L108"}, {"caller_nid": "src_init_terminate", "callee": "memset", "is_member_call": false, "source_file": "D:\\Github\\RealmCrafterOrigins\\SkeletalAnimation-master\\lib\\glfw\\src\\init.c", "source_location": "L110"}, {"caller_nid": "src_init_glfw_strdup", "callee": "strlen", "is_member_call": false, "source_file": "D:\\Github\\RealmCrafterOrigins\\SkeletalAnimation-master\\lib\\glfw\\src\\init.c", "source_location": "L120"}, {"caller_nid": "src_init_glfw_strdup", "callee": "calloc", "is_member_call": false, "source_file": "D:\\Github\\RealmCrafterOrigins\\SkeletalAnimation-master\\lib\\glfw\\src\\init.c", "source_location": "L121"}, {"caller_nid": "src_init_glfw_strdup", "callee": "strcpy", "is_member_call": false, "source_file": "D:\\Github\\RealmCrafterOrigins\\SkeletalAnimation-master\\lib\\glfw\\src\\init.c", "source_location": "L122"}, {"caller_nid": "src_init_glfwinputerror", "callee": "va_start", "is_member_call": false, "source_file": "D:\\Github\\RealmCrafterOrigins\\SkeletalAnimation-master\\lib\\glfw\\src\\init.c", "source_location": "L166"}, {"caller_nid": "src_init_glfwinputerror", "callee": "vsnprintf", "is_member_call": false, "source_file": "D:\\Github\\RealmCrafterOrigins\\SkeletalAnimation-master\\lib\\glfw\\src\\init.c", "source_location": "L167"}, {"caller_nid": "src_init_glfwinputerror", "callee": "va_end", "is_member_call": false, "source_file": "D:\\Github\\RealmCrafterOrigins\\SkeletalAnimation-master\\lib\\glfw\\src\\init.c", "source_location": "L168"}, {"caller_nid": "src_init_glfwinputerror", "callee": "strcpy", "is_member_call": false, "source_file": "D:\\Github\\RealmCrafterOrigins\\SkeletalAnimation-master\\lib\\glfw\\src\\init.c", "source_location": "L175"}, {"caller_nid": "src_init_glfwinputerror", "callee": "strcpy", "is_member_call": false, "source_file": "D:\\Github\\RealmCrafterOrigins\\SkeletalAnimation-master\\lib\\glfw\\src\\init.c", "source_location": "L177"}, {"caller_nid": "src_init_glfwinputerror", "callee": "strcpy", "is_member_call": false, "source_file": "D:\\Github\\RealmCrafterOrigins\\SkeletalAnimation-master\\lib\\glfw\\src\\init.c", "source_location": "L179"}, {"caller_nid": "src_init_glfwinputerror", "callee": "strcpy", "is_member_call": false, "source_file": "D:\\Github\\RealmCrafterOrigins\\SkeletalAnimation-master\\lib\\glfw\\src\\init.c", "source_location": "L181"}, {"caller_nid": "src_init_glfwinputerror", "callee": "strcpy", "is_member_call": false, "source_file": "D:\\Github\\RealmCrafterOrigins\\SkeletalAnimation-master\\lib\\glfw\\src\\init.c", "source_location": "L183"}, {"caller_nid": "src_init_glfwinputerror", "callee": "strcpy", "is_member_call": false, "source_file": "D:\\Github\\RealmCrafterOrigins\\SkeletalAnimation-master\\lib\\glfw\\src\\init.c", "source_location": "L185"}, {"caller_nid": "src_init_glfwinputerror", "callee": "strcpy", "is_member_call": false, "source_file": "D:\\Github\\RealmCrafterOrigins\\SkeletalAnimation-master\\lib\\glfw\\src\\init.c", "source_location": "L187"}, {"caller_nid": "src_init_glfwinputerror", "callee": "strcpy", "is_member_call": false, "source_file": "D:\\Github\\RealmCrafterOrigins\\SkeletalAnimation-master\\lib\\glfw\\src\\init.c", "source_location": "L189"}, {"caller_nid": "src_init_glfwinputerror", "callee": "strcpy", "is_member_call": false, "source_file": "D:\\Github\\RealmCrafterOrigins\\SkeletalAnimation-master\\lib\\glfw\\src\\init.c", "source_location": "L191"}, {"caller_nid": "src_init_glfwinputerror", "callee": "strcpy", "is_member_call": false, "source_file": "D:\\Github\\RealmCrafterOrigins\\SkeletalAnimation-master\\lib\\glfw\\src\\init.c", "source_location": "L193"}, {"caller_nid": "src_init_glfwinputerror", "callee": "strcpy", "is_member_call": false, "source_file": "D:\\Github\\RealmCrafterOrigins\\SkeletalAnimation-master\\lib\\glfw\\src\\init.c", "source_location": "L195"}, {"caller_nid": "src_init_glfwinputerror", "callee": "strcpy", "is_member_call": false, "source_file": "D:\\Github\\RealmCrafterOrigins\\SkeletalAnimation-master\\lib\\glfw\\src\\init.c", "source_location": "L197"}, {"caller_nid": "src_init_glfwinputerror", "callee": "strcpy", "is_member_call": false, "source_file": "D:\\Github\\RealmCrafterOrigins\\SkeletalAnimation-master\\lib\\glfw\\src\\init.c", "source_location": "L199"}, {"caller_nid": "src_init_glfwinputerror", "callee": "strcpy", "is_member_call": false, "source_file": "D:\\Github\\RealmCrafterOrigins\\SkeletalAnimation-master\\lib\\glfw\\src\\init.c", "source_location": "L201"}, {"caller_nid": "src_init_glfwinputerror", "callee": "_glfwPlatformGetTls", "is_member_call": false, "source_file": "D:\\Github\\RealmCrafterOrigins\\SkeletalAnimation-master\\lib\\glfw\\src\\init.c", "source_location": "L206"}, {"caller_nid": "src_init_glfwinputerror", "callee": "calloc", "is_member_call": false, "source_file": "D:\\Github\\RealmCrafterOrigins\\SkeletalAnimation-master\\lib\\glfw\\src\\init.c", "source_location": "L209"}, {"caller_nid": "src_init_glfwinputerror", "callee": "_glfwPlatformSetTls", "is_member_call": false, "source_file": "D:\\Github\\RealmCrafterOrigins\\SkeletalAnimation-master\\lib\\glfw\\src\\init.c", "source_location": "L210"}, {"caller_nid": "src_init_glfwinputerror", "callee": "_glfwPlatformLockMutex", "is_member_call": false, "source_file": "D:\\Github\\RealmCrafterOrigins\\SkeletalAnimation-master\\lib\\glfw\\src\\init.c", "source_location": "L211"}, {"caller_nid": "src_init_glfwinputerror", "callee": "_glfwPlatformUnlockMutex", "is_member_call": false, "source_file": "D:\\Github\\RealmCrafterOrigins\\SkeletalAnimation-master\\lib\\glfw\\src\\init.c", "source_location": "L214"}, {"caller_nid": "src_init_glfwinputerror", "callee": "strcpy", "is_member_call": false, "source_file": "D:\\Github\\RealmCrafterOrigins\\SkeletalAnimation-master\\lib\\glfw\\src\\init.c", "source_location": "L221"}, {"caller_nid": "src_init_glfwinputerror", "callee": "_glfwErrorCallback", "is_member_call": false, "source_file": "D:\\Github\\RealmCrafterOrigins\\SkeletalAnimation-master\\lib\\glfw\\src\\init.c", "source_location": "L224"}, {"caller_nid": "src_init_glfwinit", "callee": "memset", "is_member_call": false, "source_file": "D:\\Github\\RealmCrafterOrigins\\SkeletalAnimation-master\\lib\\glfw\\src\\init.c", "source_location": "L237"}, {"caller_nid": "src_init_glfwinit", "callee": "_glfwPlatformInit", "is_member_call": false, "source_file": "D:\\Github\\RealmCrafterOrigins\\SkeletalAnimation-master\\lib\\glfw\\src\\init.c", "source_location": "L240"}, {"caller_nid": "src_init_glfwinit", "callee": "_glfwPlatformCreateMutex", "is_member_call": false, "source_file": "D:\\Github\\RealmCrafterOrigins\\SkeletalAnimation-master\\lib\\glfw\\src\\init.c", "source_location": "L246"}, {"caller_nid": "src_init_glfwinit", "callee": "_glfwPlatformCreateTls", "is_member_call": false, "source_file": "D:\\Github\\RealmCrafterOrigins\\SkeletalAnimation-master\\lib\\glfw\\src\\init.c", "source_location": "L247"}, {"caller_nid": "src_init_glfwinit", "callee": "_glfwPlatformCreateTls", "is_member_call": false, "source_file": "D:\\Github\\RealmCrafterOrigins\\SkeletalAnimation-master\\lib\\glfw\\src\\init.c", "source_location": "L248"}, {"caller_nid": "src_init_glfwinit", "callee": "_glfwPlatformSetTls", "is_member_call": false, "source_file": "D:\\Github\\RealmCrafterOrigins\\SkeletalAnimation-master\\lib\\glfw\\src\\init.c", "source_location": "L254"}, {"caller_nid": "src_init_glfwinit", "callee": "_glfwPlatformGetTimerValue", "is_member_call": false, "source_file": "D:\\Github\\RealmCrafterOrigins\\SkeletalAnimation-master\\lib\\glfw\\src\\init.c", "source_location": "L257"}, {"caller_nid": "src_init_glfwinit", "callee": "glfwDefaultWindowHints", "is_member_call": false, "source_file": "D:\\Github\\RealmCrafterOrigins\\SkeletalAnimation-master\\lib\\glfw\\src\\init.c", "source_location": "L259"}, {"caller_nid": "src_init_glfwinit", "callee": "glfwUpdateGamepadMappings", "is_member_call": false, "source_file": "D:\\Github\\RealmCrafterOrigins\\SkeletalAnimation-master\\lib\\glfw\\src\\init.c", "source_location": "L266"}, {"caller_nid": "src_init_glfwgetversionstring", "callee": "_glfwPlatformGetVersionString", "is_member_call": false, "source_file": "D:\\Github\\RealmCrafterOrigins\\SkeletalAnimation-master\\lib\\glfw\\src\\init.c", "source_location": "L319"}, {"caller_nid": "src_init_glfwgeterror", "callee": "_glfwPlatformGetTls", "is_member_call": false, "source_file": "D:\\Github\\RealmCrafterOrigins\\SkeletalAnimation-master\\lib\\glfw\\src\\init.c", "source_location": "L331"}, {"caller_nid": "src_init_glfwseterrorcallback", "callee": "_GLFW_SWAP_POINTERS", "is_member_call": false, "source_file": "D:\\Github\\RealmCrafterOrigins\\SkeletalAnimation-master\\lib\\glfw\\src\\init.c", "source_location": "L348"}]}