{"nodes": [{"id": "d_github_realmcrafterorigins_skeletalanimation_master_lib_glfw_src_null_platform_h", "label": "null_platform.h", "file_type": "code", "source_file": "D:\\Github\\RealmCrafterOrigins\\SkeletalAnimation-master\\lib\\glfw\\src\\null_platform.h", "source_location": "L1"}], "edges": [{"source": "d_github_realmcrafterorigins_skeletalanimation_master_lib_glfw_src_null_platform_h", "target": "dlfcn", "relation": "imports", "context": "import", "confidence": "EXTRACTED", "source_file": "D:\\Github\\RealmCrafterOrigins\\SkeletalAnimation-master\\lib\\glfw\\src\\null_platform.h", "source_location": "L28", "weight": 1.0}, {"source": "d_github_realmcrafterorigins_skeletalanimation_master_lib_glfw_src_null_platform_h", "target": "posix_time", "relation": "imports", "context": "import", "confidence": "EXTRACTED", "source_file": "D:\\Github\\RealmCrafterOrigins\\SkeletalAnimation-master\\lib\\glfw\\src\\null_platform.h", "source_location": "L38", "weight": 1.0}, {"source": "d_github_realmcrafterorigins_skeletalanimation_master_lib_glfw_src_null_platform_h", "target": "posix_thread", "relation": "imports", "context": "import", "confidence": "EXTRACTED", "source_file": "D:\\Github\\RealmCrafterOrigins\\SkeletalAnimation-master\\lib\\glfw\\src\\null_platform.h", "source_location": "L39", "weight": 1.0}, {"source": "d_github_realmcrafterorigins_skeletalanimation_master_lib_glfw_src_null_platform_h", "target": "null_joystick", "relation": "imports", "context": "import", "confidence": "EXTRACTED", "source_file": "D:\\Github\\RealmCrafterOrigins\\SkeletalAnimation-master\\lib\\glfw\\src\\null_platform.h", "source_location": "L40", "weight": 1.0}], "raw_calls": []}