{"nodes": [{"id": "d_github_realmcrafterorigins_opengl_pbr_renderer_master_dependencies_glm_gtx_rotate_vector_hpp", "label": "rotate_vector.hpp", "file_type": "code", "source_file": "D:\\Github\\RealmCrafterOrigins\\OpenGL-PBR-Renderer-master\\dependencies\\glm\\gtx\\rotate_vector.hpp", "source_location": "L1"}], "edges": [{"source": "d_github_realmcrafterorigins_opengl_pbr_renderer_master_dependencies_glm_gtx_rotate_vector_hpp", "target": "glm", "relation": "imports", "context": "import", "confidence": "EXTRACTED", "source_file": "D:\\Github\\RealmCrafterOrigins\\OpenGL-PBR-Renderer-master\\dependencies\\glm\\gtx\\rotate_vector.hpp", "source_location": "L17", "weight": 1.0}, {"source": "d_github_realmcrafterorigins_opengl_pbr_renderer_master_dependencies_glm_gtx_rotate_vector_hpp", "target": "transform", "relation": "imports", "context": "import", "confidence": "EXTRACTED", "source_file": "D:\\Github\\RealmCrafterOrigins\\OpenGL-PBR-Renderer-master\\dependencies\\glm\\gtx\\rotate_vector.hpp", "source_location": "L18", "weight": 1.0}, {"source": "d_github_realmcrafterorigins_opengl_pbr_renderer_master_dependencies_glm_gtx_rotate_vector_hpp", "target": "rotate_vector", "relation": "imports", "context": "import", "confidence": "EXTRACTED", "source_file": "D:\\Github\\RealmCrafterOrigins\\OpenGL-PBR-Renderer-master\\dependencies\\glm\\gtx\\rotate_vector.hpp", "source_location": "L117", "weight": 1.0}], "raw_calls": []}